lenden/__init__.py
lenden/dataexport.py
lenden-0.0.1.1.dist-info/LICENSE
lenden-0.0.1.1.dist-info/METADATA
lenden-0.0.1.1.dist-info/WHEEL
lenden-0.0.1.1.dist-info/top_level.txt
lenden-0.0.1.1.dist-info/RECORD
